fathomnet/__init__.py
fathomnet/dto.py
fathomnet/util.py
fathomnet/api/__init__.py
fathomnet/api/activity.py
fathomnet/api/boundingboxes.py
fathomnet/api/comments.py
fathomnet/api/darwincore.py
fathomnet/api/firebase.py
fathomnet/api/geoimages.py
fathomnet/api/images.py
fathomnet/api/imagesetuploads.py
fathomnet/api/regions.py
fathomnet/api/stats.py
fathomnet/api/tags.py
fathomnet/api/taxa.py
fathomnet/api/topics.py
fathomnet/api/users.py
fathomnet/api/worms.py
fathomnet/api/xapikey.py
fathomnet/models/__init__.py
fathomnet/models/bases.py
fathomnet/models/yolov5.py
fathomnet/scripts/__init__.py
fathomnet/scripts/fathomnet_generate.py
fathomnet-1.9.0.dist-info/METADATA
fathomnet-1.9.0.dist-info/WHEEL
fathomnet-1.9.0.dist-info/entry_points.txt
fathomnet-1.9.0.dist-info/licenses/LICENSE
fathomnet-1.9.0.dist-info/RECORD
