Metadata-Version: 2.4
Name: fathomnet
Version: 1.9.0
Summary: fathomnet-py is a client-side API to help scientists, researchers, and developers interact with FathomNet data.
Project-URL: Homepage, https://database.fathomnet.org/fathomnet/#/about
Project-URL: Documentation, https://fathomnet-py.readthedocs.io
Project-URL: Repository, https://github.com/fathomnet/fathomnet-py.git
Project-URL: Issues, https://github.com/fathomnet/fathomnet-py/issues
Project-URL: Changelog, https://github.com/fathomnet/fathomnet-py/blob/main/CHANGELOG.md
Author-email: Kevin Barnard <kbarnard@mbari.org>
Maintainer-email: Kevin Barnard <kbarnard@mbari.org>
License-Expression: MIT
License-File: LICENSE
Classifier: License :: OSI Approved :: MIT License
Classifier: Operating System :: OS Independent
Requires-Python: >=3.8.1
Requires-Dist: coco-lib>=0.1.2
Requires-Dist: lxml>=4.6.0
Requires-Dist: progressbar2>=3.37.0
Requires-Dist: pydantic>=2.10.6
Requires-Dist: pyyaml>=6.0.1
Requires-Dist: requests>=2.20.0
Provides-Extra: models
Requires-Dist: appdirs>=1.4.4; extra == 'models'
Requires-Dist: opencv-python>=4.10.0.84; extra == 'models'
Requires-Dist: pillow>=10.4.0; extra == 'models'
Requires-Dist: torch>=2.4.0; extra == 'models'
Requires-Dist: torchvision>=0.19.0; extra == 'models'
Requires-Dist: ultralytics>=8.2.79; extra == 'models'
